MANIFEST.in
setup.py
confab/__init__.py
confab/api.py
confab/autotasks.py
confab/conffiles.py
confab/data.py
confab/definitions.py
confab/diagnostics.py
confab/diff.py
confab/files.py
confab/generate.py
confab/iter.py
confab/loaders.py
confab/main.py
confab/merge.py
confab/options.py
confab/pull.py
confab/push.py
confab/validate.py
confab.egg-info/PKG-INFO
confab.egg-info/SOURCES.txt
confab.egg-info/dependency_links.txt
confab.egg-info/entry_points.txt
confab.egg-info/requires.txt
confab.egg-info/top_level.txt
confab/tests/data/autotasks/settings.py
confab/tests/data/autotasks/settings.pyc
confab/tests/data/autotasks/settings.py~
confab/tests/data/broken/component.py
confab/tests/data/broken/component.pyc
confab/tests/data/broken/component.py~
confab/tests/data/broken/host.py_tmpl
confab/tests/data/components/role1.py
confab/tests/data/components/role1.pyc
confab/tests/data/components/role2.py
confab/tests/data/components/role2.pyc
confab/tests/data/components/role3.py
confab/tests/data/components/role3.pyc
confab/tests/data/default/broken.py
confab/tests/data/default/broken.pyc
confab/tests/data/default/empty.py
confab/tests/data/default/empty.pyc
confab/tests/data/default/example.py
confab/tests/data/default/example.pyc
confab/tests/data/default/simple.py
confab/tests/data/default/simple.pyc
confab/tests/data/multidir/components/comp1.py
confab/tests/data/multidir/components/comp1.pyc
confab/tests/data/multidir/components/comp2.py
confab/tests/data/multidir/components/comp2.pyc
confab/tests/data/multidir/roles/role1.py
confab/tests/data/multidir/roles/role1.pyc
confab/tests/data/multidir/roles/role2.py
confab/tests/data/multidir/roles/role2.pyc
confab/tests/data/order/component.py
confab/tests/data/order/component.pyc
confab/tests/data/order/default.py
confab/tests/data/order/default.pyc
confab/tests/data/order/environment.py
confab/tests/data/order/environment.pyc
confab/tests/data/order/host.py
confab/tests/data/order/host.pyc
confab/tests/data/order/role.py
confab/tests/data/order/role.pyc
confab/tests/data/templates/bar.py_tmpl
confab/tests/data/templates/baz.macro
confab/tests/data/templates/foo.py
