Metadata-Version: 1.0
Name: confab
Version: 1.4
Summary: Configuration management with Fabric and Jinja2.
Home-page: http://github.com/locationlabs/confab
Author: Location Labs
Author-email: info@locationlabs.com
License: Apache2
Platform: UNKNOWN
